rplot/__init__.py
rplot-1.8.data/scripts/rplot
rplot-1.8.dist-info/LICENSE
rplot-1.8.dist-info/METADATA
rplot-1.8.dist-info/WHEEL
rplot-1.8.dist-info/top_level.txt
rplot-1.8.dist-info/RECORD
