Metadata-Version: 2.1
Name: rplot
Version: 1.8
Summary: A stream-based realtime scientific data plotter
Home-page: https://github.com/h-ohsaki/rplot.git
Author: Hiroyuki Ohsaki
Author-email: ohsaki@lsnl.jp
License: UNKNOWN
Platform: UNKNOWN
Classifier: Programming Language :: Python :: 3
Classifier: License :: OSI Approved :: GNU General Public License v3 or later (GPLv3+)
Classifier: Operating System :: POSIX
Requires-Dist: perlcompat
Requires-Dist: pygame
Requires-Dist: tbdump
